apb_duckdb_utils/__init__.py
apb_duckdb_utils-1.1.1.dist-info/METADATA
apb_duckdb_utils-1.1.1.dist-info/WHEEL
apb_duckdb_utils-1.1.1.dist-info/top_level.txt
apb_duckdb_utils-1.1.1.dist-info/RECORD
