Metadata-Version: 2.4
Name: apb_duckdb_utils
Version: 1.1.1
Summary: DuckDB utils
Home-page: https://github.com/portdebarcelona/PLANOL-generic_python_packages/tree/master/apb_duckdb_utils_pckg
Author: Ernesto Arredondo Martínez
Author-email: ernestone@gmail.com
Maintainer: Port de Barcelona
Maintainer-email: planolport@portdebarcelona.cat
Classifier: Programming Language :: Python :: 3
Classifier: Topic :: Utilities
Classifier: Operating System :: OS Independent
Requires-Python: >=3.6
Requires-Dist: duckdb<1.5
Requires-Dist: ibis-framework[duckdb,geospatial]
Requires-Dist: duckdb-engine
Requires-Dist: polars[pyarrow]
Requires-Dist: apb_extra_utils<1.1
Requires-Dist: apb_pandas_utils<1.2
Requires-Dist: sqlglot<28.7
Dynamic: author
Dynamic: author-email
Dynamic: classifier
Dynamic: description
Dynamic: home-page
Dynamic: maintainer
Dynamic: maintainer-email
Dynamic: requires-dist
Dynamic: requires-python
Dynamic: summary
